cheesebuild/__init__.py
cheesebuild/_builder.py
cheesebuild/compilers.py
cheesebuild/project.py
cheesebuild-1.1.0.dist-info/LICENSE
cheesebuild-1.1.0.dist-info/METADATA
cheesebuild-1.1.0.dist-info/WHEEL
cheesebuild-1.1.0.dist-info/top_level.txt
cheesebuild-1.1.0.dist-info/RECORD
