Metadata-Version: 2.1
Name: cheesebuild
Version: 1.1.0
Summary: A python build system for GCC, but with CHEESE.
Author-email: afoxotter <otter@afox.page>
Project-URL: Homepage, https://github.com/chrismdjr/cheesebuild
Project-URL: Bug Tracker, https://github.com/chrismdjr/cheesebuild/issues
Classifier: Programming Language :: Python :: 3
Classifier: License :: OSI Approved :: MIT License
Classifier: Operating System :: OS Independent
Requires-Python: >=3.7
License-File: LICENSE
